multilabel_eval_metrics/__init__.py
multilabel_eval_metrics/multilabel_metrics.py
multilabel_eval_metrics/__pycache__/__init__.cpython-36.pyc
multilabel_eval_metrics/__pycache__/multilabel_metrics.cpython-36.pyc
multilabel_eval_metrics-0.0.2.dist-info/LICENSE
multilabel_eval_metrics-0.0.2.dist-info/METADATA
multilabel_eval_metrics-0.0.2.dist-info/WHEEL
multilabel_eval_metrics-0.0.2.dist-info/top_level.txt
multilabel_eval_metrics-0.0.2.dist-info/RECORD
